mockser.py
mockser-0.1.3.dist-info/METADATA
mockser-0.1.3.dist-info/RECORD
mockser-0.1.3.dist-info/WHEEL
mockser-0.1.3.dist-info/entry_points.txt
mockser-0.1.3.dist-info/top_level.txt
