Metadata-Version: 2.1
Name: mockser
Version: 0.1.3
Summary: Mock HTTP server that asks you for a JSON response everytime you visit a path for the first time.
Home-page: https://github.com/klausweiss/mockser
Author: Mikołaj Biel
License: UNKNOWN
Platform: UNKNOWN
Requires-Python: >=3
Requires-Dist: Werkzeug (==0.14.1)
